cs/app/osx/plist.py
cs.app.osx.plist-20221228.dist-info/METADATA
cs.app.osx.plist-20221228.dist-info/WHEEL
cs.app.osx.plist-20221228.dist-info/top_level.txt
cs.app.osx.plist-20221228.dist-info/RECORD
